Vedantic_AI_STT/__init_.py
vedantic_ai_stt-0.1.dist-info/METADATA
vedantic_ai_stt-0.1.dist-info/WHEEL
vedantic_ai_stt-0.1.dist-info/top_level.txt
vedantic_ai_stt-0.1.dist-info/RECORD
