Metadata-Version: 2.4
Name: Vedantic_AI_STT
Version: 0.1
Summary: this is a Vedantic AI STT package created by VYR Indurstries
Author: VYR Indrustries
Author-email: mrscientist1813@gmail.com
Dynamic: author
Dynamic: author-email
Dynamic: summary
